chimerax/__init__.py
chimerax/add_charge/5p_data.py
chimerax/add_charge/__init__.py
chimerax/add_charge/amber_name.defattr
chimerax/add_charge/charge.py
chimerax/add_charge/cmd.py
chimerax/add_charge/data.py
chimerax/add_charge/dock_prep.py
chimerax/add_charge/settings.py
chimerax/addh/__init__.py
chimerax/addh/cmd.py
chimerax/addh/dock_prep.py
chimerax/addh/hbond.py
chimerax/addh/simple.py
chimerax/addh/util.py
chimerax/alignment_algs/__init__.py
chimerax/alignment_algs/_nw.cpython-311-darwin.so
chimerax/alignment_algs/_nw.cpython-311-x86_64-linux-gnu.so
chimerax/alignment_algs/_sw.cpython-311-darwin.so
chimerax/alignment_algs/_sw.cpython-311-x86_64-linux-gnu.so
chimerax/alignment_algs/libalign_algs.dylib
chimerax/alignment_algs/libalign_algs.so
chimerax/alignment_algs/NeedlemanWunsch/__init__.py
chimerax/alignment_algs/include/align_algs/support.h
chimerax/alignment_headers/__init__.py
chimerax/alignment_headers/consensus.py
chimerax/alignment_headers/header_sequence.py
chimerax/alignment_headers/bin/al2co
chimerax/alphafold/__init__.py
chimerax/alphafold/blast.py
chimerax/alphafold/contacts.py
chimerax/alphafold/database.py
chimerax/alphafold/dimers.py
chimerax/alphafold/fetch.py
chimerax/alphafold/fetch_sequences.py
chimerax/alphafold/match.py
chimerax/alphafold/panel.py
chimerax/alphafold/predict.py
chimerax/alphafold/search.py
chimerax/altloc_explorer/__init__.py
chimerax/arrays/__init__.py
chimerax/arrays/_arrays.cpython-311-darwin.so
chimerax/arrays/_arrays.cpython-311-x86_64-linux-gnu.so
chimerax/arrays/_pyarrays.py
chimerax/arrays/include/arrays/imex.h
chimerax/arrays/include/arrays/pythonarray.h
chimerax/arrays/include/arrays/rcarray.h
chimerax/arrays/include/arrays/refcount.h
chimerax/arrays/lib/libarrays.dylib
chimerax/arrays/lib/libarrays.so
chimerax/atom_search/__init__.py
chimerax/atom_search/ast.cpython-311-darwin.so
chimerax/atom_search/ast.cpython-311-x86_64-linux-gnu.so
chimerax/atom_search/ast.pyx
chimerax/atomic/__init__.py
ChimeraX-0.1.71.dist-info/LICENSE.md
ChimeraX-0.1.71.dist-info/METADATA
ChimeraX-0.1.71.dist-info/WHEEL
ChimeraX-0.1.71.dist-info/top_level.txt
ChimeraX-0.1.71.dist-info/RECORD
